prime/__init__.py
prime/prime.py
primeuploads_py-0.0.2.dist-info/LICENSE
primeuploads_py-0.0.2.dist-info/METADATA
primeuploads_py-0.0.2.dist-info/WHEEL
primeuploads_py-0.0.2.dist-info/top_level.txt
primeuploads_py-0.0.2.dist-info/RECORD
