Metadata-Version: 2.1
Name: primeuploads-py
Version: 0.0.2
Summary: An unoffcial API wrapper for primeuploads.com
Home-page: https://github.com/CW4RR10R/primeuploads-py
Author: W4RR10R
Author-email: contact@arunpt.me
License: MIT
Platform: UNKNOWN
Classifier: Programming Language :: Python :: 3
Classifier: License :: OSI Approved :: MIT License
Classifier: Operating System :: OS Independent
Requires-Python: >=3.6
Requires-Dist: aiohttp
